setuptools_build_subpackage/__init__.py
setuptools_build_subpackage/__main__.py
setuptools_build_subpackage/_version.py
setuptools_build_subpackage/command/build.py
setuptools_build_subpackage/command/egg_info.py
setuptools_build_subpackage/command/sdist.py
setuptools_build_subpackage-1.0.0.dist-info/LICENSE
setuptools_build_subpackage-1.0.0.dist-info/METADATA
setuptools_build_subpackage-1.0.0.dist-info/WHEEL
setuptools_build_subpackage-1.0.0.dist-info/top_level.txt
setuptools_build_subpackage-1.0.0.dist-info/RECORD
