Metadata-Version: 2.1
Name: setuptools-build-subpackage
Version: 1.0.0
Summary: Package a subfolder as a python distribution
Home-page: https://github.com/ashb/setuptools-build-subpackage
Author: Ash Berlin-Taylor
Author-email: ash@apache.org
License: Apache License 2.0
Project-URL: Source Code, https://github.com/ashb/setuptools-build-subpackage
Project-URL: Bug Tracker, https://github.com/ashb/setuptools-build-subpackage/issues
Platform: UNKNOWN
Classifier: Development Status :: 5 - Production/Stable
Classifier: Intended Audience :: Developers
Classifier: License :: OSI Approved :: Apache Software License
Classifier: Operating System :: Unix
Classifier: Operating System :: POSIX
Classifier: Programming Language :: Python
Classifier: Programming Language :: Python :: 3
Classifier: Programming Language :: Python :: 3.5
Classifier: Programming Language :: Python :: 3.6
Classifier: Programming Language :: Python :: 3.7
Classifier: Programming Language :: Python :: 3.8
Classifier: Programming Language :: Python :: 3.9
Classifier: Topic :: Utilities
Requires-Python: >=3.5
Requires-Dist: setuptools (>=44.0.0)
Provides-Extra: devel
Requires-Dist: black ; extra == 'devel'
Requires-Dist: pytest-black ; extra == 'devel'
Requires-Dist: pytest-cov (~=2.10) ; extra == 'devel'
Requires-Dist: pytest-flake8 ; extra == 'devel'
Requires-Dist: pytest-isort ; extra == 'devel'
Requires-Dist: pytest (~=6.0) ; extra == 'devel'
Requires-Dist: wheel ; extra == 'devel'
